{
  "chamber": "House",
  "document_id": "house-ptr-2025-9115689",
  "filing_date": "2025-10-16",
  "ocr_engine": "tesseract 5.5.2",
  "official_id": "congress:R000395",
  "official_name": "Harold Rogers",
  "pages": [
    {
      "ocr_text": "5 sg 2 e\nptt | Bl ess | EFle>| SOSI\\PE| 2\n: y2yz> 4 gm 4\na Su 2 m\noly \u201d 72) o Sz Ny oO\no;o |} ge} oi} oe ie 8 g Ss z s Se\nol|/opl<sisc|]< ig Sees a >\nz. = 3 ) > |e Seis % g a \u201d\naejl/@e/S;jct}3 ls 2 3)e5 z a =\n\u00a9 @ 7 < QO fs a S<;OoR]}2 < fo)\nee FS) a S Cc a = a a er\noD w n = i) 2 Cc Siac]. \u00a9\nc S 5 = |? 3 BIS Ey \u00ae fe\n= = m \u00a9 = [3 2 r eyes Z \u00ae a]\nBlal/ol]s | 2 le = F4 [ ]elaele 3 of\ng g g a | 5 18 z ad Fa =/z \u00a2g 2M\nols|s|]e|3 = ~elSele 2 3 o\nz \u2019\n2,/2/Elol\u00ae le) & = Belscle A e. =\nBijr|& ele lz 2 z 1seais |e 3 ao\ns|pie@;a|SlF| 2 S e(Se12 (78 36\na/e/8/a|3 a mi a) ee |? z SY\na/<)/s |] se g IX] = af a FF\n2 | \u00a9 2 2 elfa 3 0\na s o\n\u00a9} 2 Cals o 7\n= 1h .\n_ | 2 oe es ae\naN\na 8 o se\n: 3\n~ om\n3 . a6\nwt | | | | | | reuse | pa sF| gs ro| &\n5 aay 23 g | Bo BS\n& S6o ||2 pase] 2 3 | i882 =\nst ft | TT I ccc J]e\n5\t1\t1\t1\t37\t8\t1091\t991\t50\t32\t71.740616\tSoe}\n5\t1\t1\t1\t37\t9\t1231\t987\t219\t45\t0.000000\tFelifal\n5\t1\t1\t1\t37\t10\t1570\t992\t28\t27\t22.082287\t=\n4\t1\t1\t1\t38\t0\t86\t1020\t1364\t16\t-1\t\n5\t1\t1\t1\t38\t1\t86\t1028\t23\t5\t76.405106\t=\n5\t1\t1\t1\t38\t2\t1231\t1033\t12\t3\t77.644897\t8\n5\t1\t1\t1\t38\t3\t1427\t1020\t23\t15\t88.997459\tm\n4\t1\t1\t1\t39\t0\t85\t1018\t1513\t59\t-1\t\n5\t1\t1\t1\t39\t1\t85\t1035\t24\t11\t43.609238\tst!\n5\t1\t1\t1\t39\t2\t157\t1054\t19\t14\t61.649719\t\u00a9\n5\t1\t1\t1\t39\t3\t232\t1042\t27\t35\t45.417450\tCo)\n5\t1\t1\t1\t39\t4\t314\t1054\t19\t14\t95.370888\t\u00a9\n5\t1\t1\t1\t39\t5\t654\t1049\t19\t5\t47.705406\t2\n5\t1\t1\t1\t39\t6\t775\t1047\t63\t20\t57.445251\t>a\n5\t1\t1\t1\t39\t7\t983\t1026\t14\t20\t81.842285\t=\n5\t1\t1\t1\t39\t8\t1040\t1037\t15\t25\t57.629753\t2\n5\t1\t1\t1\t39\t9\t1096\t1025\t13\t30\t70.699356\t8\n5\t1\t1\t1\t39\t10\t1125\t1023\t18\t35\t32.584862\t5\n5\t1\t1\t1\t39\t11\t1288\t1033\t12\t17\t9.738684\tg\n5\t1\t1\t1\t39\t12\t1385\t1025\t65\t28\t83.839569\tar\n5\t1\t1\t1\t39\t13\t1571\t1018\t27\t40\t61.567780\t3\n4\t1\t1\t1\t40\t0\t85\t1047\t1513\t46\t-1\t\n5\t1\t1\t1\t40\t1\t85\t1054\t408\t22\t0.000000\txrpe!e;e]e);e\n5\t1\t1\t1\t40\t2\t658\t1055\t16\t13\t88.703125\t=\n5\t1\t1\t1\t40\t3\t886\t1047\t31\t40\t8.873529\tiS)\n5\t1\t1\t1\t40\t4\t979\t1051\t20\t42\t46.680023\tg\n5\t1\t1\t1\t40\t5\t1040\t1055\t15\t21\t84.198631\t&\n5\t1\t1\t1\t40\t6\t1096\t1056\t46\t18\t50.933796\t2\n5\t1\t1\t1\t40\t7\t1288\t1055\t17\t26\t28.986292\t2\n5\t1\t1\t1\t40\t8\t1385\t1053\t65\t15\t56.811478\t=m\n5\t1\t1\t1\t40\t9\t1571\t1061\t27\t27\t90.736549\t<\n4\t1\t1\t1\t41\t0\t85\t1065\t1365\t36\t-1\t\n5\t1\t1\t1\t41\t1\t85\t1075\t170\t17\t0.000000\to}fs|;/S}]\n5\t1\t1\t1\t41\t2\t314\t1076\t20\t13\t39.449711\tns]\n5\t1\t1\t1\t41\t3\t394\t1076\t99\t14\t32.296738\tn/n\n5\t1\t1\t1\t41\t4\t538\t1069\t16\t22\t32.296738\tqs\n5\t1\t1\t1\t41\t5\t657\t1070\t16\t30\t34.411007\ts\n5\t1\t1\t1\t41\t6\t775\t1065\t139\t36\t1.121569\t820k\n5\t1\t1\t1\t41\t7\t1040\t1082\t15\t11\t77.828987\t>\n5\t1\t1\t1\t41\t8\t1092\t1072\t46\t20\t51.492085\t38\n5\t1\t1\t1\t41\t9\t1427\t1070\t23\t16\t30.664791\ta)\n4\t1\t1\t1\t42\t0\t157\t1080\t1441\t50\t-1\t\n5\t1\t1\t1\t42\t1\t157\t1091\t177\t22\t5.778198\tS/R8)/S\n5\t1\t1\t1\t42\t2\t394\t1091\t20\t21\t45.962811\t|S)\n5\t1\t1\t1\t42\t3\t474\t1091\t19\t21\t45.962811\t8\n5\t1\t1\t1\t42\t4\t538\t1093\t16\t15\t39.986397\t1s\n5\t1\t1\t1\t42\t5\t775\t1085\t139\t30\t21.295551\tSESS\n5\t1\t1\t1\t42\t6\t983\t1097\t15\t25\t12.899323\t12\n5\t1\t1\t1\t42\t7\t1040\t1094\t11\t9\t34.726048\t2\n5\t1\t1\t1\t42\t8\t1096\t1089\t95\t24\t15.728874\tSs]z\n5\t1\t1\t1\t42\t9\t1284\t1082\t20\t25\t38.536869\t3\n5\t1\t1\t1\t42\t10\t1422\t1080\t28\t50\t35.410225\tF5\n5\t1\t1\t1\t42\t11\t1571\t1089\t27\t24\t12.136030\tce\n4\t1\t1\t1\t43\t0\t79\t1098\t1519\t39\t-1\t\n5\t1\t1\t1\t43\t1\t79\t1102\t97\t32\t51.301575\tPins\n5\t1\t1\t1\t43\t2\t232\t1100\t23\t37\t29.321312\tSs\n5\t1\t1\t1\t43\t3\t314\t1113\t19\t13\t67.956039\tS\n5\t1\t1\t1\t43\t4\t390\t1100\t23\t37\t27.884798\tNS\n5\t1\t1\t1\t43\t5\t474\t1113\t19\t13\t71.957619\tS\n5\t1\t1\t1\t43\t6\t538\t1109\t16\t18\t21.370649\t[xs\n5\t1\t1\t1\t43\t7\t658\t1101\t15\t28\t66.637817\t8\n5\t1\t1\t1\t43\t8\t775\t1103\t139\t34\t34.001637\tog\u2122m\n8 Bs 3 fs} wh\noa a a a a 3 ZY 3 eee z\n= & as fe\n8. 2 ba sll) Cle 2\n= = sele\n\u201c{s|/seleaelsi\u00e9ae = o2,S9o]! - eels\n21S eS 3S 3S a |= 5 a>roi> a-]8\na}, & x x x 2 ys S a zunaSs > 58/2\nOo] 8S S S S Se i 2 99 mm 2 @e]-\nroy a a a a a a aq uo 3 gle\na $1,000- > 2 28\nce $15,000 e3\nea\ny< |$15.001- og 2 8\n$50,000 BS\nas\n$50,001- a a\n$100,000 > ey\n5\n$100,001-\n\u2014\n= awd\n$250,001. fo} _ 5 Ss\n$600,000 Fi 2 >\nx g iw] 2BSo \u00a7\na g . 8s :\n$500,001- n Ss fii 33 3\n$1,000,000 > (e) me 4 =\n$ s C= 23 5 #\n$1,000,001, ray D> ea Mai .\n$5,000,000 a = aS am 4 &\nSo Cc B 22 =\n$5,000,001- z g ao Bo\nx ey BR MN\n$25,000,000 O 4 = ~ ,\nS % mn nm & a\n$25,000,001. __ : = \u2018 B 8\n$50,000,000 a a | Ks\nOver . faa\n$50,000,000 rc",
      "page_number": 1,
      "quality": {
        "character_count": 4023,
        "field_label_confidence": {
          "amount": 0.1433,
          "asset": 0.0,
          "notification_date": 0.0,
          "owner": 0.0,
          "transaction_date": 0.1433,
          "transaction_type": 0.1433
        },
        "layout_block_count": 1,
        "layout_confidence": 0.8333,
        "line_count": 77,
        "low_confidence_word_count": 311,
        "mean_word_confidence": 42.99,
        "median_word_confidence": 41.0,
        "ocr_confidence": 0.4299,
        "ocr_text_sha256": "9b49801dd24dad54767c16baf507bd58a0046b6e819aa0b7734e57cff0819b26",
        "page_height": 2164,
        "page_width": 1676,
        "quality_score": 50.97,
        "readable_word_ratio": 0.3195,
        "review_quality_score": 0.5097,
        "review_status": "low_quality_ocr_review_required",
        "transaction_cue_hits": [],
        "transaction_form_candidate": false,
        "word_count": 457
      },
      "source_sha256": "e06b24e6d67c35b8fc96d1add91bab4617e685e8e041b355a20e482797997b07",
      "source_url": "https://disclosures-clerk.house.gov/public_disc/ptr-pdfs/2025/9115689.pdf"
    },
    {
      "ocr_text": "=o \u201ca on\ns | 845 22 ane 5 2\n= e)e> YS 3$ = =\nJ s 3 \u201c a = am |\n77) es o an ZEISS s Go ie\n2} oe |e} o |] @ TF eaigs = S\n= = = = = => g =\nQZ D 2 > s {2 $ ee PY 0 o\na|/a/eai3j\u00e96 fz 22/9 = a wn\ne@/e@/ej}salolF n &2/3z |= = e =\n2iaglo|zZ|s fe 2 = z|2< 1/5 e 8 a\nei/g};e|S | 2 IB 3 a Bifu fe Fy a ws\n8/3 /8 | Sle ig & A elszia _ = eo\n@|@/2 |= {sg \u00e9 g g725]2 2 a2\nQ 3 \u2014 > = z it\n\u00bb |e ||) e i, E m =< z]/a3]/s = 2 2m\ne/eai\u00a2g4sm @ 8 Ss isa ix 6 8 a\n7 @ \u00ae s =z > x Qo 8 a co]\no ro) z a\u00bb/[s 4I\u00a2 a s\no z B > = als = mie\no!l<; 8 5 = = sJr8le z fos\na 2 S a ~ g Sianls & oP\n3 = a N 2 g m S< Fics ]* 5 S\n= o \u00a9 a a 2 Bho Q 6 a &\n=> \u00a9 o & 3a BESS pf) e\n\u00ae/;l1/\u00b02 n 2 B2|ae =\nNo o oS Else o 7\n& io) alas Ss L-~|\n\u00b0 N ga] 2%\nios) 2 ~ Peo]\n= Oo\nBa\n3 ams\nat | | | | | | mows | 33 sz] 5 rol\nz ly goles\nBUX[X x XIX [os | 28m [lz Cea \u00a7 Fa) 8\na SZo0 e ae Zo No\nfa) ze 3 2 as \u00b0o 6S yom fen\n< EXCHANGE 2 22 3 3 a >\n= f ; P 3 S = g & am =\n= a Sz Fs 2 ||82 =\nasFe!s S S gS s S \u00a9 2S g =m\nra) nS pS nS SS wp 4s E ang \u00b0 J 2 \u00bb 88 2 uv <\nfo] D fo) D no fs Ss a> > > # sila = aa ca\nBrpyels |x}! fs 8 G2 ma\n5\t1\t1\t1\t45\t7\t989\t1115\t11\t13\t29.815464\t/}2\n5\t1\t1\t1\t45\t8\t1041\t1111\t16\t17\t60.669952\t8\n5\t1\t1\t1\t45\t9\t1102\t1110\t96\t23\t0.000000\tBF}\n5\t1\t1\t1\t45\t10\t1290\t1115\t17\t18\t69.445366\t3\n5\t1\t1\t1\t45\t11\t1433\t1112\t24\t18\t29.064655\tSo\n4\t1\t1\t1\t46\t0\t87\t1123\t1518\t34\t-1\t\n5\t1\t1\t1\t46\t1\t87\t1125\t24\t32\t32.548946\t=\n5\t1\t1\t1\t46\t2\t161\t1134\t19\t12\t25.482708\ti\n5\t1\t1\t1\t46\t3\t239\t1134\t19\t12\t93.370819\ta\n5\t1\t1\t1\t46\t4\t319\t1134\t18\t12\t70.546837\ta\n5\t1\t1\t1\t46\t5\t399\t1134\t19\t12\t37.352577\ta\n5\t1\t1\t1\t46\t6\t478\t1135\t19\t11\t90.248497\ta\n5\t1\t1\t1\t46\t7\t659\t1136\t20\t15\t42.651855\t3\n5\t1\t1\t1\t46\t8\t781\t1127\t63\t24\t47.363033\tsey\n5\t1\t1\t1\t46\t9\t989\t1129\t11\t18\t68.748940\tg\n5\t1\t1\t1\t46\t10\t1045\t1129\t15\t10\t73.390892\t3\n5\t1\t1\t1\t46\t11\t1102\t1131\t91\t25\t47.429832\t@Fls\n5\t1\t1\t1\t46\t12\t1295\t1134\t11\t9\t22.236179\t&\n5\t1\t1\t1\t46\t13\t1433\t1133\t23\t16\t63.676910\t=\n5\t1\t1\t1\t46\t14\t1577\t1123\t28\t19\t23.511791\tnN\n4\t1\t1\t1\t47\t0\t87\t1148\t1369\t28\t-1\t\n5\t1\t1\t1\t47\t1\t87\t1161\t24\t10\t94.604469\t=\n5\t1\t1\t1\t47\t2\t165\t1171\t39\t2\t58.410915\t\u2014\n5\t1\t1\t1\t47\t3\t248\t1172\t23\t1\t7.411203\tUE\n5\t1\t1\t1\t47\t4\t299\t1172\t13\t1\t0.000000\tSUR\n5\t1\t1\t1\t47\t5\t346\t1172\t30\t1\t0.000000\tTSOUNTN\n5\t1\t1\t1\t47\t6\t405\t1172\t26\t1\t0.000000\tEEO\n5\t1\t1\t1\t47\t7\t463\t1172\t24\t1\t21.858582\tSE\n5\t1\t1\t1\t47\t8\t583\t1172\t3\t1\t41.654930\ta\n5\t1\t1\t1\t47\t9\t989\t1148\t16\t28\t0.000000\tS\n5\t1\t1\t1\t47\t10\t1102\t1148\t18\t25\t16.937752\tz\n5\t1\t1\t1\t47\t11\t1131\t1159\t13\t10\t92.323502\t2\n5\t1\t1\t1\t47\t12\t1181\t1162\t12\t9\t60.749390\t2\n5\t1\t1\t1\t47\t13\t1433\t1152\t23\t22\t92.093132\tm\n4\t1\t1\t1\t48\t0\t80\t1171\t1117\t52\t-1\t\n5\t1\t1\t1\t48\t1\t80\t1174\t31\t37\t55.082932\t&\n5\t1\t1\t1\t48\t2\t659\t1193\t19\t4\t89.281921\t=\n5\t1\t1\t1\t48\t3\t762\t1191\t62\t19\t67.482986\tbu\n5\t1\t1\t1\t48\t4\t877\t1181\t24\t16\t86.714577\t=\n5\t1\t1\t1\t48\t5\t989\t1179\t11\t2\t0.000000\t.\n5\t1\t1\t1\t48\t6\t1037\t1171\t112\t52\t0.000000\t[jez\n5\t1\t1\t1\t48\t7\t1177\t1173\t20\t26\t0.000000\t|\u00a2\n4\t1\t1\t1\t49\t0\t87\t1199\t1319\t47\t-1\t\n5\t1\t1\t1\t49\t1\t87\t1202\t409\t35\t0.000000\tofe/esi/e]ai]e\n5\t1\t1\t1\t49\t2\t542\t1211\t16\t20\t33.952591\tle\n5\t1\t1\t1\t49\t3\t663\t1199\t16\t32\t48.405426\t=\n5\t1\t1\t1\t49\t4\t761\t1209\t63\t37\t63.064663\ta2\n5\t1\t1\t1\t49\t5\t876\t1200\t63\t35\t82.763397\tSo\n5\t1\t1\t1\t49\t6\t1101\t1201\t96\t29\t1.114044\ts2]3\n5\t1\t1\t1\t49\t7\t1403\t1206\t3\t2\t39.727066\t:\n4\t1\t1\t1\t50\t0\t87\t1216\t1106\t29\t-1\t\n5\t1\t1\t1\t50\t1\t87\t1241\t24\t3\t65.032028\t2\n5\t1\t1\t1\t50\t2\t156\t1216\t23\t28\t41.862740\tmn\n5\t1\t1\t1\t50\t3\t238\t1229\t20\t8\t78.994812\t=\n5\t1\t1\t1\t50\t4\t314\t1216\t23\t28\t19.769707\tg&\n5\t1\t1\t1\t50\t5\t398\t1229\t20\t8\t53.260120\ta\n5\t1\t1\t1\t50\t6\t473\t1217\t24\t28\t18.723946\tid\n5\t1\t1\t1\t50\t7\t761\t1229\t24\t16\t92.494110\t4\n5\t1\t1\t1\t50\t8\t838\t1224\t101\t21\t40.977875\toi>\n5\t1\t1\t1\t50\t9\t1101\t1224\t92\t19\t0.000000\tQAl>is\n4\t1\t1\t1\t51\t0\t86\t1233\t1107\t27\t-1\t\n5\t1\t1\t1\t51\t1\t86\t1238\t411\t22\t0.000000\ta}e|e2/s|/s]s\n5\t1\t1\t1\t51\t2\t542\t1234\t16\t21\t56.247070\t78\n5\t1\t1\t1\t51\t3\t663\t1233\t16\t23\t91.072807\t8\n5\t1\t1\t1\t51\t4\t761\t1243\t178\t15\t0.000000\tS295\n5\t1\t1\t1\t51\t5\t1102\t1240\t91\t13\t1.745424\t32]8\n4\t1\t1\t1\t52\t0\t82\t1247\t1115\t36\t-1\t\n5\t1\t1\t1\t52\t1\t82\t1247\t23\t35\t32.096474\trs\n5\t1\t1\t1\t52\t2\t160\t1247\t23\t35\t44.632473\tSs\n5\t1\t1\t1\t52\t3\t234\t1247\t23\t35\t35.816536\tnN\n5\t1\t1\t1\t52\t4\t318\t1259\t19\t12\t88.441780\tS\n5\t1\t1\t1\t52\t5\t398\t1248\t23\t35\t52.838089\tNS\n5\t1\t1\t1\t52\t6\t477\t1259\t19\t12\t33.103294\tae\n5\t1\t1\t1\t52\t7\t542\t1259\t16\t8\t10.601902\tfoo\n5\t1\t1\t1\t52\t8\t663\t1257\t16\t15\t76.759064\t=\n5\t1\t1\t1\t52\t9\t757\t1248\t33\t35\t34.785820\t[s}\n5\t1\t1\t1\t52\t10\t799\t1247\t25\t34\t52.913799\t6\n5\t1\t1\t1\t52\t11\t876\t1260\t63\t22\t84.051575\tmim\n5\t1\t1\t1\t52\t12\t1045\t1249\t16\t25\t54.256561\t5\n5\t1\t1\t1\t52\t13\t1101\t1250\t96\t25\t0.000000\tsBys\n4\t1\t1\t1\t53\t0\t86\t1266\t1107\t35\t-1\t\n5\t1\t1\t1\t53\t1\t86\t1279\t24\t22\t3.789482\ts\n5\t1\t1\t1\t53\t2\t160\t1274\t19\t13\t67.250153\ta\n5\t1\t1\t1\t53\t3\t238\t1275\t19\t12\t94.216888\ta\n5\t1\t1\t1\t53\t4\t317\t1275\t20\t12\t72.271484\ta\n5\t1\t1\t1\t53\t5\t398\t1275\t19\t12\t89.142982\ta\n5\t1\t1\t1\t53\t6\t477\t1275\t19\t12\t91.399994\ta\n5\t1\t1\t1\t53\t7\t659\t1266\t23\t32\t13.684092\tss\n5\t1\t1\t1\t53\t8\t761\t1274\t50\t16\t59.751183\tzt\n5\t1\t1\t1\t53\t9\t876\t1285\t25\t16\t77.426437\to\n5\t1\t1\t1\t53\t10\t1045\t1275\t12\t19\t50.709007\t3\n5\t1\t1\t1\t53\t11\t1101\t1277\t92\t23\t55.626736\tsls\n4\t1\t1\t1\t54\t0\t85\t1316\t1058\t40\t-1\t\n5\t1\t1\t1\t54\t1\t85\t1320\t25\t32\t80.164314\tg\n5\t1\t1\t1\t54\t2\t597\t1316\t63\t38\t56.809063\t$1,000-\n5\t1\t1\t1\t54\t3\t725\t1335\t16\t12\t96.391289\t>\n5\t1\t1\t1\t54\t4\t1044\t1330\t15\t13\t59.591713\t2\n5\t1\t1\t1\t54\t5\t1097\t1329\t46\t27\t59.591713\t23\n4\t1\t1\t1\t55\t0\t79\t1352\t1064\t30\t-1\t\n5\t1\t1\t1\t55\t1\t79\t1357\t32\t16\t11.885862\tx\n5\t1\t1\t1\t55\t2\t596\t1352\t63\t19\t85.999771\t$15,000\n5\t1\t1\t1\t55\t3\t1101\t1356\t42\t26\t0.000000\tz3\n4\t1\t1\t1\t56\t0\t1101\t1383\t46\t20\t-1\t\n5\t1\t1\t1\t56\t1\t1101\t1383\t46\t20\t50.248337\tea\n4\t1\t1\t1\t57\t0\t537\t1397\t611\t35\t-1\t\n5\t1\t1\t1\t57\t1\t537\t1397\t20\t35\t2.400913\t>\u00bb\n5\t1\t1\t1\t57\t2\t596\t1401\t69\t19\t34.648056\t$45,004-\n5\t1\t1\t1\t57\t3\t724\t1411\t16\t10\t43.393764\tw\n5\t1\t1\t1\t57\t4\t1101\t1406\t13\t26\t80.879807\t3\n5\t1\t1\t1\t57\t5\t1130\t1404\t18\t20\t33.680912\t=\n4\t1\t1\t1\t58\t0\t596\t1426\t547\t28\t-1\t\n5\t1\t1\t1\t58\t1\t596\t1426\t63\t19\t71.527374\t$60,000\n5\t1\t1\t1\t58\t2\t1101\t1431\t42\t23\t32.863155\tBB\n4\t1\t1\t1\t59\t0\t1101\t1449\t42\t20\t-1\t\n5\t1\t1\t1\t59\t1\t1101\t1449\t42\t20\t80.789139\t28\n4\t1\t1\t1\t60\t0\t595\t1470\t551\t27\t-1\t\n5\t1\t1\t1\t60\t1\t595\t1475\t70\t19\t71.656685\t$50,001-\n5\t1\t1\t1\t60\t2\t723\t1487\t16\t10\t67.317085\ta\n5\t1\t1\t1\t60\t3\t1096\t1470\t50\t25\t60.054085\tan\n4\t1\t1\t1\t61\t0\t595\t1499\t552\t23\t-1\t\n5\t1\t1\t1\t61\t1\t595\t1501\t74\t17\t86.853668\t$100,000\n5\t1\t1\t1\t61\t2\t836\t1504\t25\t18\t95.787247\t>\n5\t1\t1\t1\t61\t3\t1129\t1499\t18\t20\t14.777622\tg\n4\t1\t1\t1\t62\t0\t832\t1499\t311\t48\t-1\t\n5\t1\t1\t1\t62\t1\t832\t1499\t32\t48\t0.000000\tE=4\n5\t1\t1\t1\t62\t2\t1129\t1521\t14\t6\t64.137917\tg\n4\t1\t1\t1\t63\t0\t125\t1529\t1491\t85\t-1\t\n5\t1\t1\t1\t63\t1\t125\t1529\t103\t85\t0.000000\tPf]\n5\t1\t1\t1\t63\t2\t276\t1529\t108\t85\t13.388567\ttf\n5\t1\t1\t1\t63\t3\t432\t1534\t150\t72\t12.525330\tld\n5\t1\t1\t1\t63\t4\t595\t1549\t79\t18\t50.995693\tS250\n5\t1\t1\t1\t63\t5\t723\t1562\t16\t11\t1.276531\t.\n5\t1\t1\t1\t63\t6\t836\t1545\t25\t36\t0.000000\tS\n5\t1\t1\t1\t63\t7\t976\t1551\t65\t1\t11.442671\t_\n5\t1\t1\t1\t63\t8\t1162\t1549\t178\t3\t41.600784\ttT.\n5\t1\t1\t1\t63\t9\t1348\t1549\t133\t2\t44.930832\t(|\n5\t1\t1\t1\t63\t10\t1614\t1554\t2\t2\t57.695740\t|\n4\t1\t1\t1\t64\t0\t595\t1574\t922\t43\t-1\t\n5\t1\t1\t1\t64\t1\t595\t1574\t73\t18\t92.244072\t$250,000\n5\t1\t1\t1\t64\t2\t836\t1585\t25\t32\t92.543350\t2\n5\t1\t1\t1\t64\t3\t1175\t1582\t41\t31\t60.903198\tI\n5\t1\t1\t1\t64\t4\t1326\t1591\t23\t17\t32.758492\t=\n5\t1\t1\t1\t64\t5\t1417\t1591\t31\t24\t29.500208\tx\n5\t1\t1\t1\t64\t6\t1490\t1579\t27\t38\t37.444191\t|\n4\t1\t1\t1\t65\t0\t595\t1609\t921\t43\t-1\t\n5\t1\t1\t1\t65\t1\t595\t1623\t79\t18\t29.807037\t$250,00-\n5\t1\t1\t1\t65\t2\t836\t1626\t25\t18\t51.996273\t\u00b0\n5\t1\t1\t1\t65\t3\t973\t1643\t30\t7\t18.316555\t_\n5\t1\t1\t1\t65\t4\t1175\t1616\t40\t36\t94.412239\t>\n5\t1\t1\t1\t65\t5\t1325\t1609\t24\t36\t73.758553\t=\n5\t1\t1\t1\t65\t6\t1417\t1618\t30\t25\t73.333679\t8\n5\t1\t1\t1\t65\t7\t1490\t1619\t26\t19\t50.740677\t1a\n4\t1\t1\t1\t66\t0\t595\t1637\t920\t37\t-1\t\n5\t1\t1\t1\t66\t1\t595\t1648\t73\t18\t90.422882\t$500,000\n5\t1\t1\t1\t66\t2\t836\t1647\t25\t13\t79.111359\t7\n5\t1\t1\t1\t66\t3\t980\t1637\t27\t37\t49.175293\tFi\n5\t1\t1\t1\t66\t4\t1325\t1647\t49\t25\t80.688385\tSe\n5\t1\t1\t1\t66\t5\t1415\t1653\t30\t14\t11.600332\too\n5\t1\t1\t1\t66\t6\t1489\t1640\t26\t24\t29.183445\t|{&\n4\t1\t1\t1\t67\t0\t836\t1653\t678\t46\t-1\t\n5\t1\t1\t1\t67\t1\t836\t1668\t25\t16\t93.042114\t4\n5\t1\t1\t1\t67\t2\t975\t1662\t27\t35\t82.932892\tfo}\n5\t1\t1\t1\t67\t3\t1174\t1653\t45\t45\t37.283859\tza\n5\t1\t1\t1\t67\t4\t1323\t1671\t50\t28\t63.560192\t43\n5\t1\t1\t1\t67\t5\t1414\t1671\t31\t14\t86.676643\t2\n5\t1\t1\t1\t67\t6\t1488\t1664\t26\t33\t41.652149\t2\n4\t1\t1\t1\t68\t0\t594\t1685\t919\t44\t-1\t\n5\t1\t1\t1\t68\t1\t594\t1697\t79\t18\t5.801048\t$600,001\n5\t1\t1\t1\t68\t2\t835\t1685\t25\t37\t27.868156\tz\n5\t1\t1\t1\t68\t3\t967\t1690\t30\t29\t31.187963\t|=\n5\t1\t1\t1\t68\t4\t1173\t1695\t40\t34\t52.250717\t0\n5\t1\t1\t1\t68\t5\t1323\t1701\t49\t14\t76.304131\tem\n5\t1\t1\t1\t68\t6\t1414\t1688\t31\t15\t31.865711\ttt\n5\t1\t1\t1\t68\t7\t1487\t1697\t26\t13\t18.185787\t[a\n4\t1\t1\t1\t69\t0\t121\t1706\t1391\t42\t-1\t\n5\t1\t1\t1\t69\t1\t121\t1723\t1\t3\t29.371639\t[\n5\t1\t1\t1\t69\t2\t594\t1722\t87\t19\t1.550436\t$1,000,000\n5\t1\t1\t1\t69\t3\t835\t1724\t25\t15\t48.259541\t4\n5\t1\t1\t1\t69\t4\t979\t1706\t28\t42\t0.000000\te)\n5\t1\t1\t1\t69\t5\t1323\t1717\t49\t28\t42.920860\tawe\n5\t1\t1\t1\t69\t6\t1413\t1717\t99\t28\t49.543488\tOB\n4\t1\t1\t1\t70\t0\t835\t1746\t672\t41\t-1\t\n5\t1\t1\t1\t70\t1\t835\t1759\t24\t18\t81.535423\t>\n5\t1\t1\t1\t70\t2\t975\t1746\t25\t33\t49.133980\trel\n5\t1\t1\t1\t70\t3\t1169\t1746\t44\t41\t17.669220\tOo\n5\t1\t1\t1\t70\t4\t1322\t1758\t48\t13\t41.465359\tUs\n5\t1\t1\t1\t70\t5\t1488\t1763\t19\t7\t45.738770\tra\n4\t1\t1\t1\t71\t0\t594\t1762\t916\t37\t-1\t\n5\t1\t1\t1\t71\t1\t594\t1771\t93\t19\t25.799685\t$1,000,001\n5\t1\t1\t1\t71\t2\t835\t1762\t27\t37\t0.000000\toO\n5\t1\t1\t1\t71\t3\t979\t1776\t23\t21\t57.492676\ta\n5\t1\t1\t1\t71\t4\t1321\t1771\t49\t24\t85.409943\tme\n5\t1\t1\t1\t71\t5\t1411\t1779\t31\t16\t57.895206\two\n5\t1\t1\t1\t71\t6\t1484\t1776\t26\t13\t70.827293\tIS\n4\t1\t1\t1\t72\t0\t594\t1789\t915\t30\t-1\t\n5\t1\t1\t1\t72\t1\t594\t1797\t87\t18\t89.343842\t$5,000,000\n5\t1\t1\t1\t72\t2\t835\t1796\t24\t22\t70.476021\ta\n5\t1\t1\t1\t72\t3\t979\t1801\t23\t3\t89.247063\t=\n5\t1\t1\t1\t72\t4\t1172\t1789\t41\t30\t15.400553\tMm\n5\t1\t1\t1\t72\t5\t1321\t1790\t48\t23\t40.294662\tese\n5\t1\t1\t1\t72\t6\t1411\t1797\t30\t18\t61.828789\t=\n4\t1\t1\t1\t73\t0\t834\t1807\t658\t44\t-1\t\n5\t1\t1\t1\t73\t1\t834\t1821\t25\t18\t61.504520\t3\n5\t1\t1\t1\t73\t2\t979\t1817\t23\t18\t0.000000\t&\n5\t1\t1\t1\t73\t3\t1171\t1825\t41\t26\t22.040630\ta\n5\t1\t1\t1\t73\t4\t1319\t1807\t50\t36\t69.068794\ta2\n5\t1\t1\t1\t73\t5\t1410\t1832\t31\t16\t9.419928\tyy\n5\t1\t1\t1\t73\t6\t1482\t1816\t10\t13\t48.378212\t\u00a3\n4\t1\t1\t1\t74\t0\t593\t1870\t906\t19\t-1\t\n5\t1\t1\t1\t74\t1\t593\t1871\t98\t18\t91.970932\t$25,000,000\n5\t1\t1\t1\t74\t2\t1318\t1870\t23\t12\t39.457661\ts\n5\t1\t1\t1\t74\t3\t1409\t1870\t31\t15\t16.361866\tnm\n4\t1\t1\t1\t75\t0\t978\t1867\t627\t54\t-1\t\n5\t1\t1\t1\t75\t1\t978\t1882\t24\t39\t37.416283\t9\n5\t1\t1\t1\t75\t2\t1171\t1867\t41\t36\t92.374504\t<\n5\t1\t1\t1\t75\t3\t1301\t1882\t39\t32\t37.317413\t_B\n5\t1\t1\t1\t75\t4\t1405\t1879\t35\t36\t36.105061\t~~\n5\t1\t1\t1\t75\t5\t1590\t1898\t15\t19\t44.588608\t2\n4\t1\t1\t1\t76\t0\t593\t1906\t1008\t39\t-1\t\n5\t1\t1\t1\t76\t1\t593\t1920\t103\t18\t0.000000\t$25,000,001-\n5\t1\t1\t1\t76\t2\t972\t1925\t29\t20\t96.264153\t=\n5\t1\t1\t1\t76\t3\t1170\t1906\t41\t31\t85.463264\tm\n5\t1\t1\t1\t76\t4\t1494\t1914\t8\t8\t86.479286\t\u00b0\n5\t1\t1\t1\t76\t5\t1586\t1919\t15\t19\t56.082756\t3\n4\t1\t1\t1\t77\t0\t593\t1938\t1045\t44\t-1\t\n5\t1\t1\t1\t77\t1\t593\t1945\t97\t18\t58.289375\t$50,000,000\n5\t1\t1\t1\t77\t2\t966\t1948\t35\t19\t45.469597\ti\n5\t1\t1\t1\t77\t3\t1170\t1938\t43\t43\t90.063675\tAJ\n5\t1\t1\t1\t77\t4\t1587\t1943\t2\t13\t77.206238\t!\n5\t1\t1\t1\t77\t5\t1602\t1946\t36\t36\t0.000000\t&\n4\t1\t1\t1\t78\t0\t593\t1978\t1012\t44\t-1\t\n5\t1\t1\t1\t78\t1\t593\t1990\t37\t29\t96.915329\tOver\n5\t1\t1\t1\t78\t2\t721\t2008\t15\t8\t13.624020\te\n5\t1\t1\t1\t78\t3\t1165\t1978\t48\t44\t40.683777\tITI\n5\t1\t1\t1\t78\t4\t1587\t1990\t18\t25\t72.766136\t&\n4\t1\t1\t1\t79\t0\t592\t2007\t1046\t42\t-1\t\n5\t1\t1\t1\t79\t1\t592\t2007\t98\t39\t4.875059\t$50,000,000\n5\t1\t1\t1\t79\t2\t1175\t2022\t32\t23\t61.180542\tw\n5\t1\t1\t1\t79\t3\t1595\t2023\t43\t26\t39.512768\taad",
      "page_number": 2,
      "quality": {
        "character_count": 10726,
        "field_label_confidence": {
          "amount": 0.0,
          "asset": 0.0,
          "notification_date": 0.0,
          "owner": 0.0,
          "transaction_date": 0.0,
          "transaction_type": 0.0
        },
        "layout_block_count": 1,
        "layout_confidence": 0.8333,
        "line_count": 45,
        "low_confidence_word_count": 244,
        "mean_word_confidence": 43.43,
        "median_word_confidence": 44.02,
        "ocr_confidence": 0.4343,
        "ocr_text_sha256": "9df4e93b9622a917e01f390e94c1fd258f28e54363f25b70cb262787e3accf31",
        "page_height": 2166,
        "page_width": 1678,
        "quality_score": 51.17,
        "readable_word_ratio": 0.3222,
        "review_quality_score": 0.5117,
        "review_status": "low_quality_ocr_review_required",
        "transaction_cue_hits": [
          "exchange"
        ],
        "transaction_form_candidate": false,
        "word_count": 360
      },
      "source_sha256": "e06b24e6d67c35b8fc96d1add91bab4617e685e8e041b355a20e482797997b07",
      "source_url": "https://disclosures-clerk.house.gov/public_disc/ptr-pdfs/2025/9115689.pdf"
    },
    {
      "ocr_text": "a Se\nz a rz\n= co = \u2014\nnz =+ ole am -_\n39 g; 2 e|\u00a2 9 2\nm = | 9 ao law > o\n77] a a\n\u2014 a \u00ae a zs 2 vp)\n= Q QO nD 7\n| 8 | 2 2 & 3\neles o | 2 Z - 3 =\n\u00a9 2 21s > ve\n= = vu n fn\nfe} fe} a | @ E an a\ns S f=]\n3 | 8 8/8 A 4 8. 0\na|s co 5\ng \u00a9]: 3 2 o \u00a9\n\u00a9 8 bw 3 >\n\u00a9 3 f=.) ro} = = aa\n3 \u2014 co7 gS m o\n= = = s 3 py\n- 2 > 2 a\n2 a 2 rs\n: ae)\n\u00a7 25\n5\n3\n| 26\noo\n=| ' 32\n> ak\na PURCHASE > 4 a Nn\n3 2 &\n8 i Z\n3 279 |\nZ PEF ecce * >\n= \u2014 a ex\n5 mn S| z S208 <\ni D 2) = AroOoPF\n3 m 3 Ss 8 oa275 ei\n= a ala 3 zo \u2122 n\n= =\n= g ze rai \u00e9s\n= = oO\n$ B Z/8| & |82oa8\na id gS f=] ie ee}\nOo oo nS i] 3. 96 mm\nfey zs ata 3 zg 5\n2 o\ng Fd $1,000- >\naa a $15,000\n$15,001- 2\n$50,000\n$50,001- \u00b0\n$100,000 z\n$100,001- 3\n| | | Tt pees fg\n$250,001- Pay\n$500,000 nn\nz\n$500,001-\n$1,000,001, Fs\n$5,000,000 4\nro)\n$5,000,001- =\n$25,000,000 *\nso\n$25.000,001- \u00e9\n$50,000,000 | \u201cDd\nPt TE Pin I.",
      "page_number": 3,
      "quality": {
        "character_count": 836,
        "field_label_confidence": {
          "amount": 0.0,
          "asset": 0.0,
          "notification_date": 0.0,
          "owner": 0.0,
          "transaction_date": 0.0,
          "transaction_type": 0.0
        },
        "layout_block_count": 1,
        "layout_confidence": 0.8333,
        "line_count": 71,
        "low_confidence_word_count": 167,
        "mean_word_confidence": 50.23,
        "median_word_confidence": 51.98,
        "ocr_confidence": 0.5023,
        "ocr_text_sha256": "101b08444388c202cf6b3200eefff65b038a12aa1b5e33b58f1aaa4a64426f87",
        "page_height": 2166,
        "page_width": 1680,
        "quality_score": 47.93,
        "readable_word_ratio": 0.3927,
        "review_quality_score": 0.4793,
        "review_status": "low_quality_ocr_review_required",
        "transaction_cue_hits": [
          "purchase"
        ],
        "transaction_form_candidate": false,
        "word_count": 275
      },
      "source_sha256": "e06b24e6d67c35b8fc96d1add91bab4617e685e8e041b355a20e482797997b07",
      "source_url": "https://disclosures-clerk.house.gov/public_disc/ptr-pdfs/2025/9115689.pdf"
    },
    {
      "ocr_text": "a a\n=\nzg 8s z > 2\n2a 6 = on\nnz am |\nmo n on a a w\na @;e}/e;e;e 5 &\nm o{o|]goglo|gp 5 o\ns/s |ea|e {2 n\neje/e]/e2;\u00b0 < 8 >\nisd 8 o]| oj] o ? Fad @\nS| RF )/ eo} eye f r 3 nd\naulazajalal\u00e9a Ey > om\ng/ 3/8 /8 } 3 z A gun\ni nn oe eg mm 2 =\n2ija}; 5/8 Z 2.\na a iad oO = s = re)\n\u201clol mi ule B >\na x | a = < s = = fom\na) \u00a3 a o = m 2\u201d\n= ~ its Q = B a\nslp} @e!l13s)2 3 rs\na a SS 410 & Q lo)\n5 7 1@ls o 7\n\u00ae a a\naie OS]? poo s &\na o o\n~ \u201c e |\naA ind i 3\nz ey\na | ot | tf rome |S o\nso o2 3 es\n8 oT XLXixXi xx] | Bee Zz\n\u00ae z2\"7go -\nZ ee * Ss\n= ro =\ng x eilsis|s}\u00a2 3362\nz in s{isis{sis 223 Ee\n5 a my, 2] RLS] & So n\n= =z\no\n< g a re re ee zs ra &\n. @ sigsig/g/g Ss |Qeoa5\nz S eleleisis| & |gz%3%\ney gs a a a a a 3 2P mm\na = 7\ng Fd $1,000- >\n2 = $15,000\n$15001- ag\n$50,000\n$50,001- \u00b0\n$100,000 z\n$100.00 gg o\n\u00a2\nPt PE $50.000 z\n$250,001- oO\n$500,000 n\n2\n$500,001- :\n$4,000001- P=4\n$5,000,000 a\n$5,000,004- =\n$25,000,000 =\nos\n$25,000,001. __ 8\n$50,000,000 | &\nPT Fy finan + [.\n$50,000,000",
      "page_number": 4,
      "quality": {
        "character_count": 964,
        "field_label_confidence": {
          "amount": 0.0,
          "asset": 0.0,
          "notification_date": 0.0,
          "owner": 0.0,
          "transaction_date": 0.0,
          "transaction_type": 0.0
        },
        "layout_block_count": 1,
        "layout_confidence": 0.8333,
        "line_count": 68,
        "low_confidence_word_count": 195,
        "mean_word_confidence": 43.78,
        "median_word_confidence": 42.37,
        "ocr_confidence": 0.4378,
        "ocr_text_sha256": "b2b2638c549b46d59c90767e0e6b8096a822f471d175b2da240f8f80a932baf9",
        "page_height": 2172,
        "page_width": 1677,
        "quality_score": 42.25,
        "readable_word_ratio": 0.3085,
        "review_quality_score": 0.4225,
        "review_status": "low_quality_ocr_review_required",
        "transaction_cue_hits": [],
        "transaction_form_candidate": false,
        "word_count": 282
      },
      "source_sha256": "e06b24e6d67c35b8fc96d1add91bab4617e685e8e041b355a20e482797997b07",
      "source_url": "https://disclosures-clerk.house.gov/public_disc/ptr-pdfs/2025/9115689.pdf"
    }
  ],
  "quality": {
    "character_count": 16549,
    "field_label_confidence": {
      "amount": 0.0358,
      "asset": 0.0,
      "notification_date": 0.0,
      "owner": 0.0,
      "transaction_date": 0.0358,
      "transaction_type": 0.0358
    },
    "human_review_required": true,
    "mean_layout_confidence": 0.8333,
    "mean_ocr_confidence": 0.4511,
    "mean_page_quality_score": 48.08,
    "mean_review_quality_score": 0.4808,
    "minimum_page_quality_score": 42.25,
    "page_count": 4,
    "page_review_status_counts": {
      "low_quality_ocr_review_required": 4
    },
    "processing_status": "ocr_low_quality_review_required",
    "readable_page_count": 0,
    "transaction_rows_created": 0,
    "word_count": 1374
  },
  "review_boundary": "OCR evidence only; no transaction rows created and human review is required.",
  "schema_version": "disclosure-ocr-evidence-v2",
  "source_acquisition_status": "all_official_source_pages_acquired",
  "source_id": "house-financial-disclosure",
  "source_url": "https://disclosures-clerk.house.gov/public_disc/ptr-pdfs/2025/9115689.pdf",
  "transaction_rows_created": 0
}
